{
    "episodes": [
        {
            "id": "1399",
            "name": "Juego de tronos",
            "links": [
                {
                    "season": "1",
                    "episode": "1",
                    "urls": [
                        {
                            "quality": "Latino HD",
                            "url": "https:\/\/d0000d.com\/e\/m0hngb6tr7x3",
                            "type": "DoodStream",
                            "size": ""
                        },
                        {
                            "quality": "Latino opc 2",
                            "url": "https:\/\/wishembed.pro\/e\/cyf5s1kgiqaa",
                            "type": "Streamwish",
                            "size": ""
                        }
                    ]
                },
                {
                    "season": "1",
                    "episode": "2",
                    "urls": [
                        {
                            "quality": "Latino HD",
                            "url": "https:\/\/ds2play.com\/e\/mp2x4p76ocug",
                            "type": "DoodStream",
                            "size": ""
                        },
                        {
                            "quality": "Latino opc 2",
                            "url": "https:\/\/wishembed.pro\/e\/3lb5kmveyot9",
                            "type": "Streamwish",
                            "size": ""
                        }
                    ]
                },
                {
                    "season": "1",
                    "episode": "3",
                    "urls": [
                        {
                            "quality": "Latino HD",
                            "url": "https:\/\/ds2play.com\/e\/jt9dsh28gbwt",
                            "type": "DoodStream",
                            "size": ""
                        },
                        {
                            "quality": "Latino opc 2",
                            "url": "https:\/\/wishembed.pro\/e\/444sp3fsqq2t",
                            "type": "Streamwish",
                            "size": ""
                        }
                    ]
                },
                {
                    "season": "1",
                    "episode": "4",
                    "urls": [
                        {
                            "quality": "Latino HD",
                            "url": "https:\/\/ds2play.com\/e\/fr26x67jojpd",
                            "type": "DoodStream",
                            "size": ""
                        },
                        {
                            "quality": "Latino opc 2",
                            "url": "https:\/\/wishembed.pro\/e\/gsqpg1gsnuqr",
                            "type": "Streamwish",
                            "size": ""
                        }
                    ]
                },
                {
                    "season": "1",
                    "episode": "5",
                    "urls": [
                        {
                            "quality": "Latino HD",
                            "url": "https:\/\/ds2play.com\/e\/7d3bqli8o5r8",
                            "type": "DoodStream",
                            "size": ""
                        },
                        {
                            "quality": "Latino opc 2",
                            "url": "https:\/\/wishembed.pro\/e\/eoah60ntitu3",
                            "type": "Streamwish",
                            "size": ""
                        }
                    ]
                },
                {
                    "season": "1",
                    "episode": "6",
                    "urls": [
                        {
                            "quality": "Latino HD",
                            "url": "https:\/\/ds2play.com\/e\/uoufw5p0zhcj",
                            "type": "DoodStream",
                            "size": ""
                        },
                        {
                            "quality": "Latino opc 2",
                            "url": "https:\/\/wishembed.pro\/e\/7r43r3nf1bic",
                            "type": "Streamwish",
                            "size": ""
                        }
                    ]
                },
                {
                    "season": "1",
                    "episode": "7",
                    "urls": [
                        {
                            "quality": "Latino HD",
                            "url": "https:\/\/ds2play.com\/e\/34oz28ht4ji6",
                            "type": "DoodStream",
                            "size": ""
                        },
                        {
                            "quality": "Latino opc 2",
                            "url": "https:\/\/wishembed.pro\/e\/566ji4g83yks",
                            "type": "Streamwish",
                            "size": ""
                        }
                    ]
                },
                {
                    "season": "1",
                    "episode": "8",
                    "urls": [
                        {
                            "quality": "Latino HD",
                            "url": "https:\/\/ds2play.com\/e\/ccx7ty6b1tok",
                            "type": "DoodStream",
                            "size": ""
                        },
                        {
                            "quality": "Latino opc 2",
                            "url": "https:\/\/wishembed.pro\/e\/t927kiqfbvql",
                            "type": "Streamwish",
                            "size": ""
                        }
                    ]
                },
                {
                    "season": "1",
                    "episode": "9",
                    "urls": [
                        {
                            "quality": "Latino HD",
                            "url": "https:\/\/ds2play.com\/e\/llggz0b44gyd",
                            "type": "DoodStream",
                            "size": ""
                        },
                        {
                            "quality": "Latino opc 2",
                            "url": "https:\/\/wishembed.pro\/e\/p19rksz8h3ib",
                            "type": "Streamwish",
                            "size": ""
                        }
                    ]
                },
                {
                    "season": "1",
                    "episode": "10",
                    "urls": [
                        {
                            "quality": "Latino HD",
                            "url": "https:\/\/ds2play.com\/e\/dzdy3wf7kkui",
                            "type": "DoodStream",
                            "size": ""
                        },
                        {
                            "quality": "Latino opc 2",
                            "url": "https:\/\/wishembed.pro\/e\/lz2l3f8o3a7n",
                            "type": "Streamwish",
                            "size": ""
                        }
                    ]
                },
                {
                    "season": "2",
                    "episode": "1",
                    "urls": [
                        {
                            "quality": "Latino HD",
                            "url": "https:\/\/ds2play.com\/e\/wp91wycwjq37",
                            "type": "DoodStream",
                            "size": ""
                        },
                        {
                            "quality": "Latino opc 2",
                            "url": "https:\/\/wishembed.pro\/e\/6dl38vihzgzr",
                            "type": "Streamwish",
                            "size": ""
                        }
                    ]
                },
                {
                    "season": "2",
                    "episode": "2",
                    "urls": [
                        {
                            "quality": "Latino HD",
                            "url": "https:\/\/ds2play.com\/e\/4kad4na8707a",
                            "type": "DoodStream",
                            "size": ""
                        },
                        {
                            "quality": "Latino opc 2",
                            "url": "https:\/\/wishembed.pro\/e\/afuq4t0t984m",
                            "type": "Streamwish",
                            "size": ""
                        }
                    ]
                },
                {
                    "season": "2",
                    "episode": "3",
                    "urls": [
                        {
                            "quality": "Latino HD",
                            "url": "https:\/\/ds2play.com\/e\/0sxwnfmrfnxj",
                            "type": "DoodStream",
                            "size": ""
                        },
                        {
                            "quality": "Latino opc 2",
                            "url": "https:\/\/wishembed.pro\/e\/k8co7z5vfsir",
                            "type": "Streamwish",
                            "size": ""
                        }
                    ]
                },
                {
                    "season": "2",
                    "episode": "4",
                    "urls": [
                        {
                            "quality": "Latino HD",
                            "url": "https:\/\/ds2play.com\/e\/if4nlhye0i18",
                            "type": "DoodStream",
                            "size": ""
                        },
                        {
                            "quality": "Latino opc 2",
                            "url": "https:\/\/wishembed.pro\/e\/fdm040lmt4eq",
                            "type": "Streamwish",
                            "size": ""
                        }
                    ]
                },
                {
                    "season": "2",
                    "episode": "5",
                    "urls": [
                        {
                            "quality": "Latino HD",
                            "url": "https:\/\/ds2play.com\/e\/xg8lm630d0mt",
                            "type": "DoodStream",
                            "size": ""
                        },
                        {
                            "quality": "Latino opc 2",
                            "url": "https:\/\/wishembed.pro\/e\/j6xrw2xhobhu",
                            "type": "Streamwish",
                            "size": ""
                        }
                    ]
                },
                {
                    "season": "2",
                    "episode": "6",
                    "urls": [
                        {
                            "quality": "Latino HD",
                            "url": "https:\/\/ds2play.com\/e\/opjei4udckb3",
                            "type": "DoodStream",
                            "size": ""
                        },
                        {
                            "quality": "Latino opc 2",
                            "url": "https:\/\/wishembed.pro\/e\/vnl5sjgc4p6c",
                            "type": "Streamwish",
                            "size": ""
                        }
                    ]
                },
                {
                    "season": "2",
                    "episode": "7",
                    "urls": [
                        {
                            "quality": "Latino HD",
                            "url": "https:\/\/ds2play.com\/e\/4sewj7n86uun",
                            "type": "DoodStream",
                            "size": ""
                        },
                        {
                            "quality": "Latino opc 2",
                            "url": "https:\/\/wishembed.pro\/e\/r8ouge1womah",
                            "type": "Streamwish",
                            "size": ""
                        }
                    ]
                },
                {
                    "season": "2",
                    "episode": "8",
                    "urls": [
                        {
                            "quality": "Latino HD",
                            "url": "https:\/\/ds2play.com\/e\/e3vwpfdp0zmj",
                            "type": "DoodStream",
                            "size": ""
                        },
                        {
                            "quality": "Latino opc 2",
                            "url": "https:\/\/wishembed.pro\/e\/5fw0tde0lfmi",
                            "type": "Streamwish",
                            "size": ""
                        }
                    ]
                },
                {
                    "season": "2",
                    "episode": "9",
                    "urls": [
                        {
                            "quality": "Latino HD",
                            "url": "https:\/\/ds2play.com\/e\/dp5dejxqgsun",
                            "type": "DoodStream",
                            "size": ""
                        },
                        {
                            "quality": "Latino opc 2",
                            "url": "https:\/\/wishembed.pro\/e\/i7wf5sz7wsff",
                            "type": "Streamwish",
                            "size": ""
                        }
                    ]
                },
                {
                    "season": "2",
                    "episode": "10",
                    "urls": [
                        {
                            "quality": "Latino HD",
                            "url": "https:\/\/ds2play.com\/e\/awe7vkq94xq0",
                            "type": "DoodStream",
                            "size": ""
                        },
                        {
                            "quality": "Latino opc 2",
                            "url": "https:\/\/wishembed.pro\/e\/gbfn9an29vfs",
                            "type": "Streamwish",
                            "size": ""
                        }
                    ]
                },
                {
                    "season": "3",
                    "episode": "1",
                    "urls": [
                        {
                            "quality": "Latino HD",
                            "url": "https:\/\/uqload.to\/embed-0w5hmt7rcduw.html",
                            "type": "Uqload",
                            "size": ""
                        },
                        {
                            "quality": "Latino opc 2",
                            "url": "https:\/\/wishembed.pro\/e\/y0eghf014tr0",
                            "type": "Streamwish",
                            "size": ""
                        }
                    ]
                },
                {
                    "season": "3",
                    "episode": "2",
                    "urls": [
                        {
                            "quality": "Latino HD",
                            "url": "https:\/\/uqload.to\/embed-66wn182lucc8.html",
                            "type": "Uqload",
                            "size": ""
                        },
                        {
                            "quality": "Latino opc 2",
                            "url": "https:\/\/wishembed.pro\/e\/63fdnwsktzcb",
                            "type": "Streamwish",
                            "size": ""
                        }
                    ]
                },
                {
                    "season": "3",
                    "episode": "3",
                    "urls": [
                        {
                            "quality": "Latino HD",
                            "url": "https:\/\/uqload.to\/embed-d8v5npugwni4.html",
                            "type": "Uqload",
                            "size": ""
                        },
                        {
                            "quality": "Latino opc 2",
                            "url": "https:\/\/wishembed.pro\/e\/0tgnco8j8zar",
                            "type": "Streamwish",
                            "size": ""
                        }
                    ]
                },
                {
                    "season": "3",
                    "episode": "4",
                    "urls": [
                        {
                            "quality": "Latino HD",
                            "url": "https:\/\/uqload.to\/embed-ymgqmz6kctbl.html",
                            "type": "Uqload",
                            "size": ""
                        },
                        {
                            "quality": "Latino opc 2",
                            "url": "https:\/\/wishembed.pro\/e\/gzz6gkcrvu8u",
                            "type": "Streamwish",
                            "size": ""
                        }
                    ]
                },
                {
                    "season": "3",
                    "episode": "5",
                    "urls": [
                        {
                            "quality": "Latino HD",
                            "url": "https:\/\/uqload.to\/embed-jdwkdgp6smp5.html",
                            "type": "Uqload",
                            "size": ""
                        },
                        {
                            "quality": "Subtitulado",
                            "url": "https:\/\/wishembed.pro\/e\/7f57lpmgy1zc",
                            "type": "Streamwish",
                            "size": ""
                        }
                    ]
                },
                {
                    "season": "3",
                    "episode": "6",
                    "urls": [
                        {
                            "quality": "Latino HD",
                            "url": "https:\/\/uqload.to\/embed-5syp6dabwlg4.html",
                            "type": "Uqload",
                            "size": ""
                        },
                        {
                            "quality": "Latino opc 2",
                            "url": "https:\/\/wishembed.pro\/e\/rsxkvd9q097y",
                            "type": "Streamwish",
                            "size": ""
                        }
                    ]
                },
                {
                    "season": "3",
                    "episode": "7",
                    "urls": [
                        {
                            "quality": "Latino HD",
                            "url": "https:\/\/uqload.to\/embed-huaum8i4yihk.html",
                            "type": "Uqload",
                            "size": ""
                        },
                        {
                            "quality": "Latino opc 2",
                            "url": "https:\/\/wishembed.pro\/e\/ner428qagzyp",
                            "type": "Streamwish",
                            "size": ""
                        }
                    ]
                },
                {
                    "season": "3",
                    "episode": "8",
                    "urls": [
                        {
                            "quality": "Latino HD",
                            "url": "https:\/\/ds2play.com\/e\/69h50t4ye6gb",
                            "type": "DoodStream",
                            "size": ""
                        },
                        {
                            "quality": "Latino opc 2",
                            "url": "https:\/\/wishembed.pro\/e\/f4cv5q1m2lc4",
                            "type": "Streamwish",
                            "size": ""
                        }
                    ]
                },
                {
                    "season": "3",
                    "episode": "9",
                    "urls": [
                        {
                            "quality": "Latino HD",
                            "url": "https:\/\/uqload.to\/embed-iknpjpq75jkd.html",
                            "type": "Uqload",
                            "size": ""
                        },
                        {
                            "quality": "Latino opc 2",
                            "url": "https:\/\/wishembed.pro\/e\/q9n5qmm78f71",
                            "type": "Streamwish",
                            "size": ""
                        }
                    ]
                },
                {
                    "season": "3",
                    "episode": "10",
                    "urls": [
                        {
                            "quality": "Latino HD",
                            "url": "https:\/\/uqload.to\/embed-a0krpqbz7yk8.html",
                            "type": "Uqload",
                            "size": ""
                        },
                        {
                            "quality": "Latino opc 2",
                            "url": "https:\/\/wishembed.pro\/e\/ble97wlizpho",
                            "type": "Streamwish",
                            "size": ""
                        }
                    ]
                },
                {
                    "season": "4",
                    "episode": "1",
                    "urls": [
                        {
                            "quality": "Latino HD",
                            "url": "https:\/\/ds2play.com\/e\/h3c2y58dnc37",
                            "type": "DoodStream",
                            "size": ""
                        }
                    ]
                },
                {
                    "season": "4",
                    "episode": "2",
                    "urls": [
                        {
                            "quality": "Latino HD",
                            "url": "https:\/\/ds2play.com\/e\/bdcs3t9dact5",
                            "type": "DoodStream",
                            "size": ""
                        }
                    ]
                },
                {
                    "season": "4",
                    "episode": "3",
                    "urls": [
                        {
                            "quality": "Latino HD",
                            "url": "https:\/\/ds2play.com\/e\/da41o8oscncn",
                            "type": "DoodStream",
                            "size": ""
                        }
                    ]
                },
                {
                    "season": "4",
                    "episode": "4",
                    "urls": [
                        {
                            "quality": "Latino HD",
                            "url": "https:\/\/ds2play.com\/e\/vmjop7jsj8em",
                            "type": "DoodStream",
                            "size": ""
                        }
                    ]
                },
                {
                    "season": "4",
                    "episode": "5",
                    "urls": [
                        {
                            "quality": "Latino HD",
                            "url": "https:\/\/do0od.com\/e\/dfo8p8siert2",
                            "type": "DoodStream",
                            "size": ""
                        }
                    ]
                },
                {
                    "season": "4",
                    "episode": "6",
                    "urls": [
                        {
                            "quality": "Latino HD",
                            "url": "https:\/\/ds2play.com\/e\/9dtfqfyhubps",
                            "type": "DoodStream",
                            "size": ""
                        }
                    ]
                },
                {
                    "season": "4",
                    "episode": "7",
                    "urls": [
                        {
                            "quality": "Latino HD",
                            "url": "https:\/\/do0od.com\/e\/5uhqmpunva4h",
                            "type": "DoodStream",
                            "size": ""
                        }
                    ]
                },
                {
                    "season": "4",
                    "episode": "8",
                    "urls": [
                        {
                            "quality": "Latino HD",
                            "url": "https:\/\/do0od.com\/e\/92nwx8nzvmjl",
                            "type": "DoodStream",
                            "size": ""
                        }
                    ]
                },
                {
                    "season": "4",
                    "episode": "9",
                    "urls": [
                        {
                            "quality": "Latino HD",
                            "url": "https:\/\/do0od.com\/e\/7ypdeblpugzt",
                            "type": "DoodStream",
                            "size": ""
                        }
                    ]
                },
                {
                    "season": "4",
                    "episode": "10",
                    "urls": [
                        {
                            "quality": "Latino HD",
                            "url": "https:\/\/do0od.com\/e\/pqq2ioroe8xn",
                            "type": "DoodStream",
                            "size": ""
                        }
                    ]
                }
            ]
        },
        {
            "id": "1396",
            "name": "Breaking Bad",
            "links": [
                {
                    "season": "1",
                    "episode": "1",
                    "urls": [
                        {
                            "quality": "Latino HD",
                            "url": "https:\/\/ds2play.com\/e\/zsf4dmvrknfi",
                            "type": "DoodStream",
                            "size": ""
                        },
                        {
                            "quality": "Subtitulado HD",
                            "url": "https:\/\/ds2play.com\/e\/stahce2t6d0l",
                            "type": "DoodStream",
                            "size": ""
                        }
                    ]
                },
                {
                    "season": "1",
                    "episode": "2",
                    "urls": [
                        {
                            "quality": "Latino HD",
                            "url": "https:\/\/ds2play.com\/e\/0d8x78aqtb7s",
                            "type": "DoodStream",
                            "size": ""
                        },
                        {
                            "quality": "Subtitulado HD",
                            "url": "https:\/\/ds2play.com\/e\/yyyqcpm7hoer",
                            "type": "DoodStream",
                            "size": ""
                        }
                    ]
                },
                {
                    "season": "1",
                    "episode": "3",
                    "urls": [
                        {
                            "quality": "Latino HD",
                            "url": "https:\/\/ds2play.com\/e\/48qjk58f2jlm",
                            "type": "DoodStream",
                            "size": ""
                        }
                    ]
                },
                {
                    "season": "1",
                    "episode": "4",
                    "urls": [
                        {
                            "quality": "Latino HD",
                            "url": "https:\/\/ds2play.com\/e\/mt5t1wcsib8h",
                            "type": "DoodStream",
                            "size": ""
                        },
                        {
                            "quality": "Subtitulado HD",
                            "url": "https:\/\/ds2play.com\/e\/a4b7i1upm6hy",
                            "type": "DoodStream",
                            "size": ""
                        }
                    ]
                },
                {
                    "season": "1",
                    "episode": "6",
                    "urls": [
                        {
                            "quality": "Latino HD",
                            "url": "https:\/\/ds2play.com\/e\/4g8o5xsse637",
                            "type": "DoodStream",
                            "size": ""
                        }
                    ]
                }
            ]
        }
    ]
}
